<annotation>
	<folder>jpg Files</folder>
	<filename>1572627558597.jpg</filename>
	<path>/Users/gautamdevchowdary/Desktop/Images/drive-download-20191021T213733Z-001/jpg Files/1572627558597.jpg</path>
	<source>
		<database>Unknown</database>
	</source>
	<size>
		<width>1920</width>
		<height>1080</height>
		<depth>3</depth>
	</size>
	<segmented>0</segmented>
	<object>
		<name>p1w6grasshopper</name>
		<pose>Unspecified</pose>
		<truncated>0</truncated>
		<difficult>0</difficult>
		<bndbox>
			<xmin>1364</xmin>
			<ymin>257</ymin>
			<xmax>1525</xmax>
			<ymax>487</ymax>
		</bndbox>
	</object>
	<object>
		<name>p1w6grasshopper</name>
		<pose>Unspecified</pose>
		<truncated>0</truncated>
		<difficult>0</difficult>
		<bndbox>
			<xmin>1697</xmin>
			<ymin>463</ymin>
			<xmax>1902</xmax>
			<ymax>604</ymax>
		</bndbox>
	</object>
</annotation>
